fedora_messaging_git_hook_messages/__init__.py
fedora_messaging_git_hook_messages/base.py
fedora_messaging_git_hook_messages/commit.py
fedora_messaging_git_hook_messages-1.0.2.dist-info/METADATA
fedora_messaging_git_hook_messages-1.0.2.dist-info/WHEEL
fedora_messaging_git_hook_messages-1.0.2.dist-info/entry_points.txt
fedora_messaging_git_hook_messages-1.0.2.dist-info/top_level.txt
fedora_messaging_git_hook_messages-1.0.2.dist-info/RECORD
